[
  {
    "name": "stock images",
    "id": "stock_images",
    "credits": [
      "<a href=\"http://www.freeimages.com/photo/1152047\">Glossy Ball 1</a> by <a href=\"http://www.freeimages.com/profile/barunpatro\">Barun Patro</a>",
      
      "<a href=\"http://www.freeimages.com/photo/1326374\">Simple Swirls 1</a> by <a href=\"http://www.freeimages.com/profile/k_vohsen\">Kimberly Vohsen</a>",
      
      "<a href=\"http://www.freeimages.com/photo/746718\">Stock Portrait 4</a> by <a href=\"http://www.freeimages.com/profile/makram\">Malik Bhai</a>",
      
      "<a href=\"http://www.freeimages.com/photo/1141475\">Spontaneous</a> by <a href=\"http://www.freeimages.com/profile/bjearwicke\">Benjamin Earwicker</a>",
      
      "<a href=\"http://www.freeimages.com/photo/442249\">Kenny in London 30</a> by <a href=\"http://www.freeimages.com/profile/matchstick\">Martin Walls</a>",
      
      "<a href=\"http://www.freeimages.com/photo/1418622\">Futuristic Glasses</a> by <a href=\"http://www.freeimages.com/profile/l4red0\">Leszek Soltys</a>",
      
      "<a href=\"http://www.freeimages.com/photo/1167030\">Guy 1</a> by <a href=\"http://www.freeimages.com/profile/keenanm\">Keenan Milligan</a>",
      
      "<a href=\"http://www.freeimages.com/photo/1168191\">Smiling So Happy</a> by <a href=\"http://www.freeimages.com/profile/jvangalen\">Jos van Galen</a>",
      
      "<a href=\"http://www.freeimages.com/photo/1166915\">Tomasito Superstar</a> by <a href=\"http://www.freeimages.com/profile/coloniera2\">Hector Landaeta</a>",
      
      "<a href=\"http://www.freeimages.com/photo/1363173\">Rural Self Portrait</a> by <a href=\"http://www.freeimages.com/profile/colinbroug\">Colin Brough</a>",
      
      "<a href=\"http://www.freeimages.com/photo/1287009\">Coffee Smile</a> by <a href=\"http://www.freeimages.com/profile/michaelaw\">Michaela Kobyakov</a>",
      
      "Striped background created with <a href=\"http://www.stripegenerator.com/\">Stripe Generator</a>"
    ]
  },{
    "name": "fonts",
    "id": "fonts",
    "credits": [
      "<a href=\"http://www.google.com/fonts/specimen/Open+Sans\">Open Sans</a> designed by <a href=\"https://profiles.google.com/107777320916704234605/about\">Steve Matteson</a>, &copy; 2010-2011 Google Corporation",
      
      "<a href=\"http://www.google.com/fonts/specimen/Montserrat\">Montserrat</a> &copy; 2012 Julieta Ulanovsky",
      
      "Dosis &copy; <a href=\"https://plus.google.com/114391601624281927771/about\">Pablo Impallari</a>",
      
      "Nunito &copy; <a href=\"https://plus.google.com/+vernonadams/about\">Vernon Adams</a>",
      
      "<a href=\"http://fontawesome.io\">Font Awesome</a> &copy; 2012-2015 Dave Gandy"
    ]
  },{
    "name": "libraries",
    "id": "libraries",
    "credits": [
      "<a href=\"http://foundation.zurb.com/\">Foundation</a> &copy; 2014 ZURB",
           
      "<a href=\"https://angularjs.org/\">AngularJS</a> &copy; 2010-2015 Google, Inc.",
      
      "<a href=\"https://pineconellc.github.io/angular-foundation/\">Angular Foundation</a> &copy; 2014 Pinecone, LLC",
      
      "<a href=\"https://angular-ui.github.io/\">AngularUI</a> &copy; 2012-2015 the AngularUI Team",
      
      "<a href=\"http://sass-lang.com/\">Sass</a> &copy; 2006-2015 <a href=\"//www.hamptoncatlin.com/\">Hampton Catlin</a>, <a href=\"//nex-3.com/\">Natalie Weizenbaum</a>, <a href=\"//chriseppstein.github.io/\">Chris Eppstein</a>, and numerous contributors.<br/><a href=\"http://compass-style.org/\">Compass</a> &copy; 2008-2015 Chris Eppstein."
    ]
  },{
    "name": "song lyrics",
    "id": "song_lyrics",
    "credits": [
      "<p><a href=\"https://www.youtube.com/watch?v=GyV_UG60dD4\"><cite>Mission Statement</cite></a> lyrics &copy; 2014 \"Weird Al\" Yankovic</p>"
    ]
  }
]